MANIFEST.in
README.md
requirements.txt
setup.py
hnelib/__init__.py
hnelib/color.py
hnelib/legend.py
hnelib/model.py
hnelib/pandas.py
hnelib/plot.py
hnelib/runner.py
hnelib/stats.py
hnelib/utils.py
hnelib.egg-info/PKG-INFO
hnelib.egg-info/SOURCES.txt
hnelib.egg-info/dependency_links.txt
hnelib.egg-info/requires.txt
hnelib.egg-info/top_level.txt
hnelib/pd/__init__.py
hnelib/pd/annotate.py
hnelib/pd/util.py
hnelib/plt/__init__.py
hnelib/plt/arrow.py
hnelib/plt/ax.py
hnelib/plt/color.py
hnelib/plt/dims.py
hnelib/plt/font.py
hnelib/plt/grid.py
hnelib/plt/legend.py
hnelib/plt/lim.py
hnelib/plt/scatter.py
hnelib/stat/__init__.py
hnelib/stat/model.py
hnelib/stat/test.py